<?xml version="1.0" encoding="UTF-8"?>
<vra xmlns="https://www.loc.gov/standards/vracore/schemas.html" xmlns:ext="http://exist-db.org/vra/extension" xmlns:hra="http://cluster-schemas.uni-hd.de" xmlns:xsi="http://www.w3.org/2001/XMLSchema-instance" xsi:schemaLocation="https://www.loc.gov/standards/vracore/schemas.html http://cluster-schemas.uni-hd.de/vra-strictCluster.xsd">
    <image id="i_5f2befda-0e86-3fc7-9478-719e8a3f174c" source="Tamboti-Importer" href="hra-imageserver://kjc-sv016/commons/Abou_Naddara/Journals/1879/1_Abou-Naddara-Zarqa_issues-001-030/issue_018/1879_0072_018_003.tif">
        <titleSet>
            <title type="generalView">1879_0072_018_003.tif (image record)</title>
        </titleSet>
        <relationSet>
            <relation type="imageOf" relids="w_db9f2d08-b56a-3395-aa1f-653abe2bb07d" source="Tamboti-Importer">full view</relation>
        </relationSet>
    </image>
</vra>