<?xml version="1.0" encoding="UTF-8"?>
<vra xmlns="https://www.loc.gov/standards/vracore/schemas.html" xmlns:ext="http://exist-db.org/vra/extension" xmlns:hra="http://cluster-schemas.uni-hd.de" xmlns:xsi="http://www.w3.org/2001/XMLSchema-instance" xsi:schemaLocation="https://www.loc.gov/standards/vracore/schemas.html http://cluster-schemas.uni-hd.de/vra-strictCluster.xsd">
    <work id="w_4a7a2568-d5d2-3efc-969d-2749806185a9" source="Tamboti-Importer">
        <titleSet>
            <title type="generalView">1895_0013_002_003.tif</title>
        </titleSet>
        <relationSet>
            <relation type="imageIs" relids="i_09ecac4f-aa3e-3ad5-9280-6be2701193b0" source="Tamboti-Importer">full view</relation>
            <relation type="relatedTo" href="uuid-91dd633f-7f46-413f-9d7b-829d64b92b32" pref="false">Tamboti MODS record</relation>
        </relationSet>
    </work>
</vra>