<?xml version="1.0" encoding="UTF-8"?>
<vra xmlns="http://www.vraweb.org/vracore4.htm" xmlns:ext="http://exist-db.org/vra/extension" xmlns:hra="http://cluster-schemas.uni-hd.de" xmlns:xsi="http://www.w3.org/2001/XMLSchema-instance" xsi:schemaLocation="http://www.vraweb.org/vracore4.htm http://cluster-schemas.uni-hd.de/vra-strictCluster.xsd">
    <image id="i_a2b1a6e6-7eee-3717-889f-a5fefe890ae3" source="Tamboti-Importer" href="hra-imageserver://kjc-sv016/commons/Abou_Naddara/Journals/1885/1_Le-Journal-d-Abou-Naddara_issues-001-012/issue_003/1885_0012_003_002.tif">
        <titleSet>
            <title type="generalView">1885_0012_003_002.tif (image record)</title>
        </titleSet>
        <relationSet>
            <relation type="imageOf" relids="w_b70ad125-eaf9-3f7c-8ee7-08d428a77a80" source="Tamboti-Importer">full view</relation>
        </relationSet>
    </image>
</vra>