<?xml version="1.0" encoding="UTF-8"?>
<vra xmlns="https://www.loc.gov/standards/vracore/schemas.html" xmlns:ext="http://exist-db.org/vra/extension" xmlns:hra="http://cluster-schemas.uni-hd.de" xmlns:xsi="http://www.w3.org/2001/XMLSchema-instance" xsi:schemaLocation="https://www.loc.gov/standards/vracore/schemas.html http://cluster-schemas.uni-hd.de/vra-strictCluster.xsd">
    <work id="w_5bf78310-01dc-3f48-b80b-26fe292c4829" source="Tamboti-Importer">
        <titleSet>
            <title type="generalView">1893_0023_006_001.tif</title>
        </titleSet>
        <relationSet>
            <relation type="imageIs" relids="i_c944247d-5223-31a7-866b-9b0920081275" source="Tamboti-Importer">full view</relation>
            <relation type="relatedTo" href="uuid-1dc5a187-8390-4423-aae3-10de175d5256" pref="false">Tamboti MODS record</relation>
        </relationSet>
    </work>
</vra>