<?xml version="1.0" encoding="UTF-8"?>
<vra xmlns="http://www.vraweb.org/vracore4.htm" xmlns:ext="http://exist-db.org/vra/extension" xmlns:hra="http://cluster-schemas.uni-hd.de" xmlns:xsi="http://www.w3.org/2001/XMLSchema-instance" xsi:schemaLocation="http://www.vraweb.org/vracore4.htm http://cluster-schemas.uni-hd.de/vra-strictCluster.xsd">
    <work id="w_8b9aaa99-acb1-3d7c-8429-9511fb63948d" source="Tamboti-Importer">
        <titleSet>
            <title type="generalView">1886_0047_012_001.tif</title>
        </titleSet>
        <relationSet>
            <relation type="imageIs" relids="i_1a2536c9-362f-3240-87a2-c097aa8bf12a" source="Tamboti-Importer">full view</relation>
            <relation type="relatedTo" href="uuid-3e5ebe73-ed62-452a-88e7-21b5511e50af" pref="false">Tamboti MODS record</relation>
        </relationSet>
    </work>
</vra>