<?xml version="1.0" encoding="UTF-8"?>
<vra xmlns="http://www.vraweb.org/vracore4.htm" xmlns:ext="http://exist-db.org/vra/extension" xmlns:hra="http://cluster-schemas.uni-hd.de" xmlns:xsi="http://www.w3.org/2001/XMLSchema-instance" xsi:schemaLocation="http://www.vraweb.org/vracore4.htm http://cluster-schemas.uni-hd.de/vra-strictCluster.xsd">
    <work id="w_b4e60363-14e2-3db5-99e1-4f0aeb644e54" source="Tamboti-Importer">
        <titleSet>
            <title type="generalView">1885_0013_003_003.tif</title>
        </titleSet>
        <relationSet>
            <relation type="imageIs" relids="i_4aac48d6-4009-3e61-a322-d5fbcf6f91f8" source="Tamboti-Importer">full view</relation>
            <relation type="relatedTo" href="uuid-e904ee68-83e5-4d4a-bd32-f84b0f669c1b" pref="false">Tamboti MODS record</relation>
        </relationSet>
    </work>
</vra>