<?xml version="1.0" encoding="UTF-8"?>
<vra xmlns="https://www.loc.gov/standards/vracore/schemas.html" xmlns:ext="http://exist-db.org/vra/extension" xmlns:hra="http://cluster-schemas.uni-hd.de" xmlns:xsi="http://www.w3.org/2001/XMLSchema-instance" xsi:schemaLocation="https://www.loc.gov/standards/vracore/schemas.html http://cluster-schemas.uni-hd.de/vra-strictCluster.xsd">
    <image id="i_3e3ed0c9-7b4c-3e22-b8df-e59d4565ed1a" source="Tamboti-Importer" href="hra-imageserver://kjc-sv016/commons/Abou_Naddara/Journals/1884/1_Abou-Naddara_issues-001-010/issue_003/1884_0011_003_003.tif">
        <titleSet>
            <title type="generalView">1884_0011_003_003.tif (image record)</title>
        </titleSet>
        <relationSet>
            <relation type="imageOf" relids="w_c88fafcd-9b53-3c7d-98de-78b17e004a1c" source="Tamboti-Importer">full view</relation>
        </relationSet>
    </image>
</vra>