<?xml version="1.0" encoding="UTF-8"?>
<mods xmlns="http://www.loc.gov/mods/v3" xmlns:xlink="http://www.w3.org/1999/xlink" xmlns:xsi="http://www.w3.org/2001/XMLSchema-instance" xsi:schemaLocation="http://www.loc.gov/standards/mods/v3/mods-3-6.xsd" ID="uuid-294c5058-c10f-40ef-b72a-55cb7fc1ad2b">
    <titleInfo lang="ara" script="arab">
        <title>جريدة ابي نظارة</title>
        <subTitle>مصر للمصرين</subTitle>
    </titleInfo>
    <titleInfo type="translated" lang="arab" transliteration="arabic/ala-lc">
        <title>garīdat abī naẓẓāra</title>
        <subTitle>miṣr li-l-miṣrīyn</subTitle>
    </titleInfo>
    <titleInfo type="alternative" lang="fre">
        <title>Le Journal d'Abou Naddara</title>
        <subTitle>Abou Naddara
L'Egypte aux Egyptiens</subTitle>
    </titleInfo>
    <titleInfo type="translated" lang="eng">
        <title>The Journal of the Man with the  Glasses</title>
        <subTitle>Egypt for the Egyptians</subTitle>
    </titleInfo>
    <name type="personal" xlink:href="#uuid-7743b9b1-21c3-4472-83f8-65ce81cab817"/>
    <originInfo>
        <place>
            <placeTerm type="text">Paris</placeTerm>
        </place>
        <dateIssued encoding="w3cdtf" keyDate="yes">1892</dateIssued>
    </originInfo>
    <physicalDescription>
        <extent unit="pages">4</extent>
        <note lang="eng" displayLabel="Page range as printed"/>
        <digitalOrigin>reformatted digital</digitalOrigin>
    </physicalDescription>
    <targetAudience authority="marctarget">adult</targetAudience>
    <typeOfResource>text</typeOfResource>
    <genre authority="marcgt">issue</genre>
    <subject xlink:href="#uuid-dda4b333-f72e-48f3-999d-66c7454c9097"/>
    <note type="edition" displayLabel="Additional western date information">16ème Année
Directeur et rédacteur en Chef J. Sanua Abou Naddara
6, Rue Geoffroy -Marie, Paris </note>
    <note type="edition" displayLabel="Additional Arabic date information">جريدة ابي نظارة
السنة السادسة عشر
مدير الجريدة و محررها الاول 
الشيخ ج. سانوا ابو نظارة نمرة ٦ رو جوفروا ماري بباريس </note>
    <note type="edition" displayLabel="Western date as printed">Paris, le 25 Juillet 1892</note>
    <note type="edition" displayLabel="Arabic date as printed">باريس في ٢٥ لوليو  سنة ١٨٩٢ </note>
    <relatedItem xlink:href="#uuid-dd67546e-93ee-487e-b2fe-fc4f1a94c3bc" displayLabel="Part of published series" type="series">
        <part>
            <detail type="issue">
                <number>14</number>
                <number lang="ara" script="arab">عدد ١٤</number>
            </detail>
            <extent unit="pages">
                <total>4</total>
                <list/>
            </extent>
            <date encoding="w3cdtf">1892-07-25</date>
        </part>
    </relatedItem>
    <location>
        <url displayLabel="Path to Folder">issue_014</url>
    </location>
    <language>
        <languageTerm authority="iso639-2b" type="code">fre</languageTerm>
        <scriptTerm authority="iso15924" type="code">latn</scriptTerm>
    </language>
    <language>
        <languageTerm authority="iso639-2b" type="code">ara</languageTerm>
        <scriptTerm authority="iso15924" type="code">arab</scriptTerm>
    </language>
    <recordInfo lang="eng" script="latn">
        <recordContentSource authority="marcorg">DE-16-158</recordContentSource>
        <recordCreationDate encoding="w3cdtf">2011-08-27+02:00</recordCreationDate>
        <languageOfCataloging>
            <languageTerm authority="iso639-2b" type="code">eng</languageTerm>
            <scriptTerm authority="iso15924" type="code">latn</scriptTerm>
        </languageOfCataloging>
    </recordInfo>
    <extension xmlns:e="http://www.asia-europe.uni-heidelberg.de/">
        <e:naddara>
            <western_sorting displayLabel="Western sorting of issue">yes</western_sorting>
            <Jahr displayLabel="Year">1892</Jahr>
            <Monat displayLabel="Month">7</Monat>
            <Tag displayLabel="Day">25</Tag>
            <UUID displayLabel="UUID of this record">294c5058-c10f-40ef-b72a-55cb7fc1ad2b</UUID>
            <host_folder displayLabel="folder-name of host record">1_Le-Journal-d-Abou-Naddara_issues-001-024</host_folder>
        </e:naddara>
    </extension>
    <note type="edition" displayLabel="Western date as printed">Paris, le 25 Juillet 1892</note>
    <note type="edition" displayLabel="Arabic date as printed">باريس في ٢٥ لوليو  سنة ١٨٩٢ </note>
    <relatedItem type="constituent" displayLabel="Page" xlink:href="#w_ad4bf515-8640-392b-b655-e7d44dea8af8">
        <typeOfResource>still image</typeOfResource>
        <identifier type="local">w_ad4bf515-8640-392b-b655-e7d44dea8af8</identifier>
        <titleInfo>
            <title>1892_0055_014_001.tif</title>
        </titleInfo>
        <part>
            <detail type="page number">
                <number>1</number>
            </detail>
        </part>
    </relatedItem>
    <note type="edition" displayLabel="Western date as printed">Paris, le 25 Juillet 1892</note>
    <note type="edition" displayLabel="Arabic date as printed">باريس في ٢٥ لوليو  سنة ١٨٩٢ </note>
    <relatedItem type="constituent" displayLabel="Page" xlink:href="#w_33dc834f-2317-3c9f-a301-fc1b2c4e331a">
        <typeOfResource>still image</typeOfResource>
        <identifier type="local">w_33dc834f-2317-3c9f-a301-fc1b2c4e331a</identifier>
        <titleInfo>
            <title>1892_0056_014_002.tif</title>
        </titleInfo>
        <part>
            <detail type="page number">
                <number>2</number>
            </detail>
        </part>
    </relatedItem>
    <note type="edition" displayLabel="Western date as printed">Paris, le 25 Juillet 1892</note>
    <note type="edition" displayLabel="Arabic date as printed">باريس في ٢٥ لوليو  سنة ١٨٩٢ </note>
    <relatedItem type="constituent" displayLabel="Page" xlink:href="#w_fa886e9a-1d00-39ec-bd00-084d95ad07a8">
        <typeOfResource>still image</typeOfResource>
        <identifier type="local">w_fa886e9a-1d00-39ec-bd00-084d95ad07a8</identifier>
        <titleInfo>
            <title>1892_0057_014_003.tif</title>
        </titleInfo>
        <part>
            <detail type="page number">
                <number>3</number>
            </detail>
        </part>
    </relatedItem>
    <note type="edition" displayLabel="Western date as printed">Paris, le 25 Juillet 1892</note>
    <note type="edition" displayLabel="Arabic date as printed">باريس في ٢٥ لوليو  سنة ١٨٩٢ </note>
    <relatedItem type="constituent" displayLabel="Page" xlink:href="#w_40f3f06b-6aa2-3071-9f50-42dfc53661c2">
        <typeOfResource>still image</typeOfResource>
        <identifier type="local">w_40f3f06b-6aa2-3071-9f50-42dfc53661c2</identifier>
        <titleInfo>
            <title>1892_0058_014_004.tif</title>
        </titleInfo>
        <part>
            <detail type="page number">
                <number>4</number>
            </detail>
        </part>
    </relatedItem>
</mods>