<?xml version="1.0" encoding="UTF-8"?>
<vra xmlns="https://www.loc.gov/standards/vracore/schemas.html" xmlns:ext="http://exist-db.org/vra/extension" xmlns:hra="http://cluster-schemas.uni-hd.de" xmlns:xsi="http://www.w3.org/2001/XMLSchema-instance" xsi:schemaLocation="https://www.loc.gov/standards/vracore/schemas.html http://cluster-schemas.uni-hd.de/vra-strictCluster.xsd">
    <work id="w_611da5eb-5176-39b6-928c-d775e1cff7bb" source="Tamboti-Importer">
        <titleSet>
            <title type="generalView">1878_0018_005_001.tif</title>
        </titleSet>
        <relationSet>
            <relation type="imageIs" relids="i_a951385a-fe0d-3fa0-bfea-63d1694f2c0a" source="Tamboti-Importer">full view</relation>
            <relation type="relatedTo" href="uuid-f4b6e908-7056-4666-9406-343c0337a7a4" pref="false">Tamboti MODS record</relation>
        </relationSet>
    </work>
</vra>