<?xml version="1.0" encoding="UTF-8"?>
<vra xmlns="https://www.loc.gov/standards/vracore/schemas.html" xmlns:ext="http://exist-db.org/vra/extension" xmlns:hra="http://cluster-schemas.uni-hd.de" xmlns:xsi="http://www.w3.org/2001/XMLSchema-instance" xsi:schemaLocation="https://www.loc.gov/standards/vracore/schemas.html http://cluster-schemas.uni-hd.de/vra-strictCluster.xsd">
    <image id="i_9ffe6f4f-5625-39cd-a1a3-1d0e067f0bf4" source="Tamboti-Importer" href="hra-imageserver://kjc-sv016/commons/Abou_Naddara/Journals/1903/1_Le-Journal-d-Abou-Naddara_issues-001-005/issue_001/1903_0003_001_001.tif">
        <titleSet>
            <title type="generalView">1903_0003_001_001.tif (image record)</title>
        </titleSet>
        <relationSet>
            <relation type="imageOf" relids="w_3ae66cb1-a1ce-3f87-85cb-f68cf9a7a081" source="Tamboti-Importer">full view</relation>
        </relationSet>
    </image>
</vra>