<?xml version="1.0" encoding="UTF-8"?>
<vra xmlns="https://www.loc.gov/standards/vracore/schemas.html" xmlns:ext="http://exist-db.org/vra/extension" xmlns:hra="http://cluster-schemas.uni-hd.de" xmlns:xsi="http://www.w3.org/2001/XMLSchema-instance" xsi:schemaLocation="https://www.loc.gov/standards/vracore/schemas.html http://cluster-schemas.uni-hd.de/vra-strictCluster.xsd">
    <image id="i_b665ba0b-0058-3df2-af75-da7860a0ce44" source="Tamboti-Importer" href="hra-imageserver://kjc-sv016/commons/Abou_Naddara/Journals/1888/2_L-Attawadod_issues-001-012/issue_003/1888_0049_003_015.tif">
        <titleSet>
            <title type="generalView">1888_0049_003_015.tif (image record)</title>
        </titleSet>
        <relationSet>
            <relation type="imageOf" relids="w_51f26c27-909c-314f-80ff-9197bdc09de0" source="Tamboti-Importer">full view</relation>
        </relationSet>
    </image>
</vra>